{
  "schema_version": "1.0",
  "package_name": "CAMEX Fund Characteristics",
  "generated_on": "2026-03-23",
  "status": "proposed_pre_launch",
  "detail_level": "starter_profile",
  "scope_definition": "54_sovereign_african_states_build",
  "fund_identity": {
    "fund_name": "CAMEX Fund",
    "short_name": "CAMEX",
    "full_name": "Cameroon Raw Export Index Fund",
    "benchmark_ticker": "CAMEX",
    "fund_status": "not_yet_constituted",
    "target_domicile": "Cameroon",
    "iso3": "CMR",
    "base_currency": "XAF",
    "regional_comparison_currency": "XAF",
    "continental_comparison_currency": "USD"
  },
  "fund_family": {"family_code": "AFEX", "subfamily_code": "CAEX", "family_role": "diversified_anchor_member"},
  "benchmark_methodology": {"index_code": "CAMEX", "methodology_model": "coastal_export_model", "methodology_status": "starter_profile_needs_country_trade_validation"},
  "candidate_constituent_universe": [
    {"name": "Crude Oil", "status": "candidate"},
    {"name": "Cocoa Beans", "status": "candidate"},
    {"name": "Timber", "status": "candidate"},
    {"name": "Raw Cotton", "status": "candidate"},
    {"name": "Coffee", "status": "candidate"},
    {"name": "Natural Gas", "status": "candidate"}
  ],
  "country_context": {
    "subfamily_code": "CAEX",
    "regional_links": ["Nigeria", "Chad", "Central African Republic", "Gabon", "Equatorial Guinea"],
    "special_note": "Cameroon should combine energy, timber, and agricultural export logic."
  },
  "research_and_validation": {"validation_status": "under_research"},
  "regulatory_positioning": {"generic_note": "Country-specific legal review required.", "microfinance_separation_note": "Fund vehicle should remain separate from any microfinance balance sheet."}
}
